arc_advisor/__init__.py
arc_advisor/cli.py
arc_advisor/client.py
arc_advisor/multi_agent_hub.py
arc_advisor/protocols.py
arc_advisor/tool_advisor.py
arc_advisor/vector_store.py
arc_advisor-0.1.0.dist-info/licenses/LICENSE
arc_advisor-0.1.0.dist-info/METADATA
arc_advisor-0.1.0.dist-info/WHEEL
arc_advisor-0.1.0.dist-info/entry_points.txt
arc_advisor-0.1.0.dist-info/top_level.txt
arc_advisor-0.1.0.dist-info/RECORD
