Metadata-Version: 2.4
Name: arc-advisor
Version: 0.1.0
Summary: The learning co-pilot for AI agents. Implements the Executor-Advisor pattern for building self-improving agentic systems.
Author-email: The Arc AI Team <team@arc.computer>
License:                                  Apache License
Project-URL: Homepage, https://arc.computer
Project-URL: Documentation, https://docs.arc.computer
Project-URL: Repository, https://github.com/arc-ai/arc-advisor
Project-URL: Issues, https://github.com/arc-ai/arc-advisor/issues
Keywords: ai,agents,machine-learning,reinforcement-learning,llm,advisor,executor
Classifier: Programming Language :: Python :: 3
Classifier: Programming Language :: Python :: 3.9
Classifier: Programming Language :: Python :: 3.10
Classifier: Programming Language :: Python :: 3.11
Classifier: Programming Language :: Python :: 3.12
Classifier: License :: OSI Approved :: Apache Software License
Classifier: Operating System :: OS Independent
Classifier: Development Status :: 4 - Beta
Classifier: Intended Audience :: Developers
Classifier: Topic :: Software Development :: Libraries :: Python Modules
Classifier: Topic :: Scientific/Engineering :: Artificial Intelligence
Requires-Python: >=3.9
License-File: LICENSE
Requires-Dist: requests>=2.28.0
Requires-Dist: huggingface_hub>=0.20.0
Requires-Dist: torch>=2.0.0
Requires-Dist: transformers>=4.38.0
Requires-Dist: pydantic>=2.0
Requires-Dist: chromadb>=0.4.0
Requires-Dist: sentence-transformers>=2.2.0
Provides-Extra: examples
Requires-Dist: openai>=1.0.0; extra == "examples"
Requires-Dist: python-dotenv>=1.0.0; extra == "examples"
Dynamic: license-file
